aibloks/__init__.py
aibloks/client.py
aibloks/errors.py
aibloks/instantai.py
aibloks/libraries.py
aibloks/library.py
aibloks/requestor.py
aibloks-0.9.1.dist-info/LICENSE.txt
aibloks-0.9.1.dist-info/METADATA
aibloks-0.9.1.dist-info/WHEEL
aibloks-0.9.1.dist-info/top_level.txt
aibloks-0.9.1.dist-info/zip-safe
aibloks-0.9.1.dist-info/RECORD
