Metadata-Version: 2.1
Name: aibloks
Version: 0.9.1
Summary: Client library for the Ai Bloks REST API
Home-page: https://www.aibloks.com
Author-email: support@aibloks.com
Project-URL: Repository, https://github.com/aibloks/aibloks-python-sdk
Keywords: ai,data,development
Classifier: Development Status :: 4 - Beta
Classifier: Intended Audience :: Developers
Classifier: Topic :: Software Development
Classifier: License :: OSI Approved :: MIT License
Classifier: Programming Language :: Python :: 3.6
Classifier: Programming Language :: Python :: 3.7
Classifier: Programming Language :: Python :: 3.8
Classifier: Programming Language :: Python :: 3.9
Classifier: Programming Language :: Python :: 3.10
Classifier: Programming Language :: Python :: 3.11
Requires-Python: >=3.6, <4
License-File: LICENSE.txt
